bsm_library01/__init__.py
bsm_library01/aidsu.py
bsm_library01/module.py
bsm_library01-0.1.2.dist-info/METADATA
bsm_library01-0.1.2.dist-info/WHEEL
bsm_library01-0.1.2.dist-info/top_level.txt
bsm_library01-0.1.2.dist-info/RECORD
