Metadata-Version: 2.1
Name: bsm-library01
Version: 0.1.2
Summary: Testing library for BSM AIDSU
Home-page: https://github.com/yourusername/my_library
Author: JR
Author-email: jefri.ronaldo@banksinarmas.com
License: UNKNOWN
Platform: UNKNOWN
Classifier: Programming Language :: Python :: 3
Classifier: License :: OSI Approved :: MIT License
Classifier: Operating System :: OS Independent
Requires-Python: >=3.9
Requires-Dist: flask
